pytest_pretty/__init__.py
pytest_pretty-1.2.0.dist-info/METADATA
pytest_pretty-1.2.0.dist-info/WHEEL
pytest_pretty-1.2.0.dist-info/entry_points.txt
pytest_pretty-1.2.0.dist-info/licenses/LICENSE
pytest_pretty-1.2.0.dist-info/RECORD
